<annotation>
	<folder>JPEGImages</folder>
	<filename>img_38.jpg</filename>
	<path>C:\Users\Posedion\Desktop\毕业设计\label_thin\label_thin\VOCdevkit\VOC2012\JPEGImages\img_38.jpg</path>
	<source>
		<database>Unknown</database>
	</source>
	<size>
		<width>293</width>
		<height>220</height>
		<depth>3</depth>
	</size>
	<segmented>0</segmented>
	<object>
		<name>other_waste</name>
		<pose>Unspecified</pose>
		<truncated>1</truncated>
		<difficult>0</difficult>
		<bndbox>
			<xmin>1</xmin>
			<ymin>2</ymin>
			<xmax>118</xmax>
			<ymax>215</ymax>
		</bndbox>
	</object>
	<object>
		<name>other_waste</name>
		<pose>Unspecified</pose>
		<truncated>1</truncated>
		<difficult>0</difficult>
		<bndbox>
			<xmin>130</xmin>
			<ymin>1</ymin>
			<xmax>280</xmax>
			<ymax>220</ymax>
		</bndbox>
	</object>
	<object>
		<name>kitchen_waste</name>
		<pose>Unspecified</pose>
		<truncated>0</truncated>
		<difficult>0</difficult>
		<bndbox>
			<xmin>143</xmin>
			<ymin>26</ymin>
			<xmax>265</xmax>
			<ymax>122</ymax>
		</bndbox>
	</object>
</annotation>
