<annotation>
	<folder>JPEGImages</folder>
	<filename>img_23.jpg</filename>
	<path>C:\Users\Posedion\Desktop\毕业设计\label_thin\label_thin\VOCdevkit\VOC2012\JPEGImages\img_23.jpg</path>
	<source>
		<database>Unknown</database>
	</source>
	<size>
		<width>500</width>
		<height>500</height>
		<depth>3</depth>
	</size>
	<segmented>0</segmented>
	<object>
		<name>other_waste</name>
		<pose>Unspecified</pose>
		<truncated>0</truncated>
		<difficult>0</difficult>
		<bndbox>
			<xmin>27</xmin>
			<ymin>50</ymin>
			<xmax>289</xmax>
			<ymax>443</ymax>
		</bndbox>
	</object>
	<object>
		<name>other_waste</name>
		<pose>Unspecified</pose>
		<truncated>0</truncated>
		<difficult>0</difficult>
		<bndbox>
			<xmin>307</xmin>
			<ymin>43</ymin>
			<xmax>497</xmax>
			<ymax>441</ymax>
		</bndbox>
	</object>
</annotation>
